cofunctions.py
cofunctions-2023.2.1.dist-info/LICENSE
cofunctions-2023.2.1.dist-info/WHEEL
cofunctions-2023.2.1.dist-info/METADATA
cofunctions-2023.2.1.dist-info/RECORD
