Metadata-Version: 2.1
Name: cofunctions
Version: 2023.2.1
Summary: cofunction: simple coroutines
Keywords: generators,coroutines
Author-email: Nicolas Tessore <n.tessore@ucl.ac.uk>
Requires-Python: >=3.6
Classifier: License :: OSI Approved :: MIT License
Project-URL: Home, https://github.com/ntessore/cofunctions
Project-URL: Issues, https://github.com/ntessore/cofunctions/issues
